trueform/_version.py
trueform/_io.py
trueform/__init__.py
trueform/distance_field.py
trueform/distance.py
trueform/_trueform.cpython-311-darwin.so
trueform/intersects.py
trueform/ray_cast.py
trueform/_dispatch/ensure_mesh.py
trueform/_dispatch/__init__.py
trueform/_dispatch/canonicalize.py
trueform/_dispatch/suffix.py
trueform/_dispatch/meta.py
trueform/_spatial/point_cloud.py
trueform/_spatial/__init__.py
trueform/_spatial/mesh.py
trueform/_spatial/_dispatch.py
trueform/_spatial/gather_ids.py
trueform/_spatial/_validation.py
trueform/_spatial/edge_mesh.py
trueform/_spatial/neighbor_search.py
trueform/cmake/__init__.py
trueform/cmake/__main__.py
trueform/_core/offset_blocked_array.py
trueform/_core/closest_metric_point_pair.py
trueform/_core/__init__.py
trueform/_core/_dispatch.py
trueform/_core/as_offset_blocked.py
trueform/_core/transformed.py
trueform/_reindex/split_into_components.py
trueform/_reindex/concatenated.py
trueform/_reindex/__init__.py
trueform/_reindex/reindex_by_ids.py
trueform/_reindex/reindex_by_mask_on_points.py
trueform/_reindex/reindex_by_mask.py
trueform/_reindex/reindex_by_ids_on_points.py
trueform/include/trueform/topology.hpp
trueform/include/trueform/trueform.hpp
trueform/include/trueform/io.hpp
trueform/include/trueform/version.hpp
trueform/include/trueform/clean.hpp
trueform/include/trueform/random.hpp
trueform/include/trueform/reindex.hpp
trueform/include/trueform/cut.hpp
trueform/include/trueform/intersect.hpp
trueform/include/trueform/geometry.hpp
trueform/include/trueform/spatial.hpp
trueform/include/trueform/core.hpp
trueform/include/trueform/topology/set_component_labels.hpp
trueform/include/trueform/topology/connected_component_labels.hpp
trueform/include/trueform/topology/non_simple_edges.hpp
trueform/include/trueform/topology/are_oriented_faces_equal.hpp
trueform/include/trueform/topology/edge_id_in_face.hpp
trueform/include/trueform/topology/edge_membership_like.hpp
trueform-0.3.0.dist-info/RECORD
trueform-0.3.0.dist-info/WHEEL
trueform-0.3.0.dist-info/METADATA
trueform-0.3.0.dist-info/licenses/LICENSE
trueform-0.3.0.dist-info/licenses/LICENSE.noncommercial
trueform-0.3.0.dist-info/licenses/licenses/LICENSE.nanobind
trueform-0.3.0.dist-info/licenses/licenses/LICENSE.TBB
