Metadata-Version: 2.2
Name: trueform
Version: 0.3.0
Summary: Real-time geometric processing on NumPy arrays. Easy to use, robust on real-world data.
Keywords: mesh,geometry,computational-geometry,mesh-processing,mesh-boolean,collision-detection,point-cloud,csg,numpy
Author: XLAB
Author-Email: Ziga Sajovic <info@polydera.com>
License: # PolyForm Noncommercial License 1.0.0
Classifier: Development Status :: 4 - Beta
Classifier: Intended Audience :: Developers
Classifier: Intended Audience :: Science/Research
Classifier: License :: Other/Proprietary License
Classifier: Operating System :: OS Independent
Classifier: Programming Language :: Python
Classifier: Programming Language :: Python :: 3
Classifier: Programming Language :: Python :: 3 :: Only
Classifier: Programming Language :: Python :: 3.9
Classifier: Programming Language :: Python :: 3.10
Classifier: Programming Language :: Python :: 3.11
Classifier: Programming Language :: Python :: 3.12
Classifier: Programming Language :: Python :: 3.13
Classifier: Programming Language :: Python :: 3.14
Classifier: Topic :: Scientific/Engineering :: Mathematics
Classifier: Topic :: Scientific/Engineering :: Visualization
Project-URL: Homepage, https://trueform.polydera.com
Project-URL: Documentation, https://trueform.polydera.com
Project-URL: Repository, https://github.com/polydera/trueform
Project-URL: Issues, https://github.com/polydera/trueform/issues
Requires-Python: >=3.9
Requires-Dist: numpy>=1.23
